AUT/RedPulse/__init__.py
AUT/RedPulse/actions.py
AUT/RedPulse/pages.py
AUT/RedPulse/test_cases.py
Execution/Sample/__init__.py
pyselenium_framework-0.2.0.dist-info/METADATA
pyselenium_framework-0.2.0.dist-info/RECORD
pyselenium_framework-0.2.0.dist-info/WHEEL
pyselenium_framework-0.2.0.dist-info/top_level.txt
selenium_framework/__init__.py
selenium_framework/common.py
selenium_framework/identifier.py
selenium_framework/reporting.py
selenium_framework/utils.py
selenium_framework/web_browser.py
selenium_framework/web_element.py
selenium_framework/third_party/__init__.py
selenium_framework/third_party/pyExcelerator/BIFFRecords.py
selenium_framework/third_party/pyExcelerator/Bitmap.py
selenium_framework/third_party/pyExcelerator/Cell.py
selenium_framework/third_party/pyExcelerator/Column.py
selenium_framework/third_party/pyExcelerator/CompoundDoc.py
selenium_framework/third_party/pyExcelerator/Deco.py
selenium_framework/third_party/pyExcelerator/ExcelFormula.py
selenium_framework/third_party/pyExcelerator/ExcelFormulaLexer.py
selenium_framework/third_party/pyExcelerator/ExcelFormulaParser.py
selenium_framework/third_party/pyExcelerator/ExcelMagic.py
selenium_framework/third_party/pyExcelerator/Formatting.py
selenium_framework/third_party/pyExcelerator/ImportXLS.py
selenium_framework/third_party/pyExcelerator/Row.py
selenium_framework/third_party/pyExcelerator/Style.py
selenium_framework/third_party/pyExcelerator/UnicodeUtils.py
selenium_framework/third_party/pyExcelerator/Utils.py
selenium_framework/third_party/pyExcelerator/Workbook.py
selenium_framework/third_party/pyExcelerator/Worksheet.py
selenium_framework/third_party/pyExcelerator/__init__.py
selenium_framework/third_party/pyExcelerator/antlr.py
