Metadata-Version: 2.1
Name: pyselenium-framework
Version: 0.2.0
Summary: A Python Selenium Framework Which Makes Code More Easy to Maintain and Read
Home-page: https://github.com/wally-yu/selenium-framework
Author: Wally Yu
License: MIT License
Platform: UNKNOWN
Requires-Dist: selenium (==3.14.1)
